ozobot/common/__init__.py
ozobot/common/asyncutils.py
ozobot/common/broadcast.py
ozobot/common/convert.py
ozobot/common/crc.py
ozobot/common/exceptions.py
ozobot/common/logging.py
ozobot/common/match.py
ozobot/common/py.typed
ozobot/common/rlock.py
ozobot/common/types.py
ozobot_common-0.1.2.dist-info/METADATA
ozobot_common-0.1.2.dist-info/WHEEL
ozobot_common-0.1.2.dist-info/RECORD
